transformersplus/__init__.py
transformersplus/__version__.py
transformersplus/models/__init__.py
transformersplus/models/bright_albert/__init__.py
transformersplus/models/bright_albert/convert_bright_albert_origin_tf_checkpoint_to_pytorch.py
transformersplus/models/bright_albert/modeling_bright_albert.py
transformersplus/utils/__init__.py
transformersplus/utils/triton.py
transformersplus-0.2.0.dist-info/LICENSE
transformersplus-0.2.0.dist-info/METADATA
transformersplus-0.2.0.dist-info/WHEEL
transformersplus-0.2.0.dist-info/top_level.txt
transformersplus-0.2.0.dist-info/RECORD
